[
  {
    "period": "2024 Aug 1-2025 July 31",
    "stock": "JSWHL",
    "sector": "Finance - Investment - Management",
    "index": "SmallCap 250",
    "returns": 187.98
  },
  {
    "period": "2024 Aug 1-2025 July 31",
    "stock": "BSE",
    "sector": "Finance - Investment - Management",
    "index": "Midcap 150 Index",
    "returns": 175.66
  },
  {
    "period": "2024 Aug 1-2025 July 31",
    "stock": "AIIL",
    "sector": "Finance - Investment - Management",
    "index": "SmallCap 250",
    "returns": 162.74
  },
  {
    "period": "2024 Aug 1-2025 July 31",
    "stock": "CARTRADE",
    "sector": "Auto",
    "index": "Nifty Microcap 250",
    "returns": 151.95
  },
  {
    "period": "2024 Aug 1-2025 July 31",
    "stock": "PARADEEP",
    "sector": "Fertilizers - Pesticides",
    "index": "Nifty Microcap 250",
    "returns": 138.48
  },
  {
    "period": "2024 Aug 1-2025 July 31",
    "stock": "WEBELSOLAR",
    "sector": "IT - Hardware",
    "index": "Nifty Microcap 250",
    "returns": 123.00
  },
  {
    "period": "2024 Aug 1-2025 July 31",
    "stock": "PAYTM",
    "sector": "Finance - Investment - Management",
    "index": "Midcap 150 Index",
    "returns": 119.58
  },
  {
    "period": "2024 Aug 1-2025 July 31",
    "stock": "GODFRYPHLP",
    "sector": "Tobacco - Alcohol",
    "index": "SmallCap 250",
    "returns": 115.27
  },
  {
    "period": "2024 Aug 1-2025 July 31",
    "stock": "GABRIEL",
    "sector": "Auto Ancillary",
    "index": "Nifty Microcap 250",
    "returns": 110.15
  },
  {
    "period": "2024 Aug 1-2025 July 31",
    "stock": "SHARDACROP",
    "sector": "Fertilizers - Pesticides",
    "index": "Nifty Microcap 250",
    "returns": 103.89
  },
  {
    "period": "2024 Aug 1-2025 July 31",
    "stock": "ACUTAAS",
    "sector": null,
    "index": null,
    "returns": 98.35
  },
  {
    "period": "2024 Aug 1-2025 July 31",
    "stock": "TI",
    "sector": "Tobacco - Alcohol",
    "index": "Nifty Microcap 250",
    "returns": 98.31
  },
  {
    "period": "2024 Aug 1-2025 July 31",
    "stock": "LAURUSLABS",
    "sector": "Pharma",
    "index": "SmallCap 250",
    "returns": 94.80
  },
  {
    "period": "2024 Aug 1-2025 July 31",
    "stock": "LLOYDSME",
    "sector": "Metals - Steel - Iron Products",
    "index": "Midcap 150 Index",
    "returns": 92.94
  },
  {
    "period": "2024 Aug 1-2025 July 31",
    "stock": "SHAILY",
    "sector": "Plastic",
    "index": "Nifty Microcap 250",
    "returns": 91.18
  },
  {
    "period": "2024 Aug 1-2025 July 31",
    "stock": "CHOICEIN",
    "sector": "Finance - Stock Broking",
    "index": "Nifty Microcap 250",
    "returns": 90.80
  },
  {
    "period": "2024 Aug 1-2025 July 31",
    "stock": "PGEL",
    "sector": "Consumer Durables",
    "index": "SmallCap 250",
    "returns": 87.72
  },
  {
    "period": "2024 Aug 1-2025 July 31",
    "stock": "WOCKPHARMA",
    "sector": "Pharma",
    "index": "SmallCap 250",
    "returns": 87.56
  },
  {
    "period": "2024 Aug 1-2025 July 31",
    "stock": "AMBER",
    "sector": "Consumer Durables",
    "index": "SmallCap 250",
    "returns": 86.79
  },
  {
    "period": "2024 Aug 1-2025 July 31",
    "stock": "FORCEMOT",
    "sector": "Auto",
    "index": "Nifty Microcap 250",
    "returns": 84.76
  }
]
